LICENSE
MANIFEST.in
README.md
README.rst
setup.cfg
setup.py
netwulf/__init__.py
netwulf/interactive.py
netwulf/metadata.py
netwulf/tools.py
netwulf.egg-info/PKG-INFO
netwulf.egg-info/SOURCES.txt
netwulf.egg-info/dependency_links.txt
netwulf.egg-info/not-zip-safe
netwulf.egg-info/requires.txt
netwulf.egg-info/top_level.txt
netwulf/js/.git
netwulf/js/.gitignore
netwulf/js/LICENSE
netwulf/js/README.md
netwulf/js/index.html
netwulf/js/parse_options.js
netwulf/js/post_json.js
netwulf/js/style.css
netwulf/js/test.json
netwulf/js/vis.js
netwulf/js/libs/d3.v4.min.js
netwulf/js/libs/dat.gui.js
netwulf/js/libs/lodash.js
netwulf/js/libs/sweetalert2.all.min.js
netwulf/tests/__init__.py
netwulf/tests/test_all.py