Metadata-Version: 1.2
Name: netwulf
Version: 0.1.2
Summary: Interactively visualize networks with Ulf Aslak's d3-tool from Python.
Home-page: https://github.com/benmaier/netwulf
Author: Ulf Aslak, Benjamin F. Maier
Author-email: bfmaier@physik.hu-berlin.de
License: MIT
Project-URL: Documentation, https://netwulf.rtfd.io
Project-URL: Contributing Statement, https://github.com/benmaier/netwulf/blob/master/CONTRIBUTING.md
Project-URL: Bug Reports, https://github.com/benmaier/netwulf/issues
Project-URL: Source, https://github.com/benmaier/netwulf/
Project-URL: PyPI, https://pypi.org/project/netwulf/
Platform: UNKNOWN
Classifier: License :: OSI Approved :: MIT License
Classifier: Programming Language :: Python :: 3.5
Classifier: Programming Language :: Python :: 3.6
Classifier: Programming Language :: Python :: 3.7
Requires-Python: ~=3.5
